MANIFEST.in
README.md
setup.py
whirl/__init__.py
whirl/_version.py
whirl/cookie.py
whirl/httpmessage.py
whirl/parsers.py
whirl/tornado_server.py
whirl/url.py
whirl.egg-info/PKG-INFO
whirl.egg-info/SOURCES.txt
whirl.egg-info/dependency_links.txt
whirl.egg-info/top_level.txt